neumf/__init__.py
neumf/settings.py
neumf/utils.py
neumf/data/NegativeTransactionTable.py
neumf/data/TransactionSequence.py
neumf/data/__init__.py
neumf/data/pipelines.py
neumf/data/transform.py
neumf/data/utils.py
neumf/model/NeuMF.py
neumf/model/__init__.py
neumf/model/gpus.py
neumf/model/layers.py
neumf/model/loss.py
neumf/model/utils.py
neumf-0.0.7.dist-info/METADATA
neumf-0.0.7.dist-info/WHEEL
neumf-0.0.7.dist-info/top_level.txt
neumf-0.0.7.dist-info/RECORD
