Metadata-Version: 2.1
Name: neumf
Version: 0.0.7
Summary: neumf module
Home-page: https://pypi.org/project/neumf/
Author: Sumner Magruder
Author-email: sumner.magruder@zmnh.uni-hamburg.de
License: UNKNOWN
Platform: UNKNOWN
Classifier: Programming Language :: Python :: 3.6
Classifier: License :: OSI Approved :: MIT License
Classifier: Operating System :: OS Independent
